setup.py
pruner/__init__.py
pruner/pruner.py
pruner.egg-info/PKG-INFO
pruner.egg-info/SOURCES.txt
pruner.egg-info/dependency_links.txt
pruner.egg-info/entry_points.txt
pruner.egg-info/requires.txt
pruner.egg-info/top_level.txt