Metadata-Version: 1.0
Name: pruner
Version: 0.0.6
Summary: A CLI tool for pruning your overgrown requirements file
Home-page: https://github.com/mattjegan/pruner
Author: Matthew Egan
Author-email: matthewj.egan@hotmai.com
License: UNKNOWN
Platform: UNKNOWN
